PythonRengongzhinengZhongwenbanChuyiFix1/README.md
PythonRengongzhinengZhongwenbanChuyiFix1/__init__.py
PythonRengongzhinengZhongwenbanChuyiFix1/__main__.py
PythonRengongzhinengZhongwenbanChuyiFix1/file.epub
PythonRengongzhinengZhongwenbanChuyiFix1/index.html
PythonRengongzhinengZhongwenbanChuyiFix1/css/__init__.py
PythonRengongzhinengZhongwenbanChuyiFix1/css/annotations.css
PythonRengongzhinengZhongwenbanChuyiFix1/css/main.css
PythonRengongzhinengZhongwenbanChuyiFix1/css/normalize.css
PythonRengongzhinengZhongwenbanChuyiFix1/css/popup.css
PythonRengongzhinengZhongwenbanChuyiFix1/font/__init__.py
PythonRengongzhinengZhongwenbanChuyiFix1/font/fontello.eot
PythonRengongzhinengZhongwenbanChuyiFix1/font/fontello.svg
PythonRengongzhinengZhongwenbanChuyiFix1/font/fontello.ttf
PythonRengongzhinengZhongwenbanChuyiFix1/font/fontello.woff
PythonRengongzhinengZhongwenbanChuyiFix1/img/__init__.py
PythonRengongzhinengZhongwenbanChuyiFix1/img/annotator-glyph-sprite.png
PythonRengongzhinengZhongwenbanChuyiFix1/img/annotator-icon-sprite.png
PythonRengongzhinengZhongwenbanChuyiFix1/img/apple-touch-icon.png
PythonRengongzhinengZhongwenbanChuyiFix1/img/cancelfullscreen.png
PythonRengongzhinengZhongwenbanChuyiFix1/img/close.png
PythonRengongzhinengZhongwenbanChuyiFix1/img/fullscreen.png
PythonRengongzhinengZhongwenbanChuyiFix1/img/loader.gif
PythonRengongzhinengZhongwenbanChuyiFix1/img/menu-icon.png
PythonRengongzhinengZhongwenbanChuyiFix1/img/save.png
PythonRengongzhinengZhongwenbanChuyiFix1/img/saved.png
PythonRengongzhinengZhongwenbanChuyiFix1/img/settings-s.png
PythonRengongzhinengZhongwenbanChuyiFix1/img/settings.png
PythonRengongzhinengZhongwenbanChuyiFix1/img/star.png
PythonRengongzhinengZhongwenbanChuyiFix1/js/__init__.py
PythonRengongzhinengZhongwenbanChuyiFix1/js/epub.js
PythonRengongzhinengZhongwenbanChuyiFix1/js/epub.min.js
PythonRengongzhinengZhongwenbanChuyiFix1/js/epub.min.map
PythonRengongzhinengZhongwenbanChuyiFix1/js/hooks.min.js
python_rengongzhineng_zhongwenban_chuyi_fix1-2025.3.24.0.dist-info/METADATA
python_rengongzhineng_zhongwenban_chuyi_fix1-2025.3.24.0.dist-info/WHEEL
python_rengongzhineng_zhongwenban_chuyi_fix1-2025.3.24.0.dist-info/entry_points.txt
python_rengongzhineng_zhongwenban_chuyi_fix1-2025.3.24.0.dist-info/top_level.txt
python_rengongzhineng_zhongwenban_chuyi_fix1-2025.3.24.0.dist-info/RECORD
